web_command/__init__.py
web_command/console.py
web_command/server.py
web_command/static/default.html
web_command/static/web-command.css
web_command/static/web-command.js
web_command-0.1.0.dist-info/entry_points.txt
web_command-0.1.0.dist-info/LICENSE
web_command-0.1.0.dist-info/WHEEL
web_command-0.1.0.dist-info/METADATA
web_command-0.1.0.dist-info/RECORD
