Metadata-Version: 2.1
Name: web-command
Version: 0.1.0
Summary: Output a command to a web browser.
Home-page: https://github.com/vjagaro/web-command
License: ISC
Author: Jāgaro
Author-email: v.jagaro@gmail.com
Requires-Python: >=3.5.3,<4.0.0
Classifier: License :: OSI Approved
Classifier: Programming Language :: Python :: 3
Classifier: Programming Language :: Python :: 3.6
Classifier: Programming Language :: Python :: 3.7
Classifier: Programming Language :: Python :: 3.8
Requires-Dist: aiohttp (>=3.0,<4.0)
Requires-Dist: ansicolors (>=1.0,<2.0)
Requires-Dist: ptyprocess (>=0.6,<0.7)
Project-URL: Repository, https://github.com/vjagaro/web-command
